github_repo_files_parser/__init__.py
github_repo_files_parser/github_repo_files_parser.py
github_repo_files_parser-1.0.1.dist-info/METADATA
github_repo_files_parser-1.0.1.dist-info/WHEEL
github_repo_files_parser-1.0.1.dist-info/top_level.txt
github_repo_files_parser-1.0.1.dist-info/RECORD
