Metadata-Version: 2.1
Name: github-repo-files-parser
Version: 1.0.1
Summary: Extract file paths from GitHub repositories categorized by extension
Author: Paurush Kumar
Project-URL: Documentation, https://pypi.org/project/github_repo_files_parser/
Project-URL: Source, https://pypi.org/project/github_repo_files_parser/
